personal_chat_slm/__init__.py
personal_chat_slm/clean_logic.py
personal_chat_slm/cli.py
personal_chat_slm/generate_logic.py
personal_chat_slm/model.py
personal_chat_slm/train_logic.py
personal_chat_slm-0.1.2.dist-info/METADATA
personal_chat_slm-0.1.2.dist-info/WHEEL
personal_chat_slm-0.1.2.dist-info/entry_points.txt
personal_chat_slm-0.1.2.dist-info/top_level.txt
personal_chat_slm-0.1.2.dist-info/RECORD
