Metadata-Version: 2.4
Name: personal-chat-slm
Version: 0.1.2
Summary: A nano-LLM trained from scratch on personal chat data to mimic a conversational style.
Author-email: Prayas Gautam <prayas12gautam@gmail.com>
License: MIT License
Project-URL: Homepage, https://github.com/Imprayas12/personal-chat-slm
Project-URL: Bug Tracker, https://github.com/Imprayas12/personal-chat-slm/issues
Classifier: Programming Language :: Python :: 3
Classifier: License :: OSI Approved :: MIT License
Classifier: Operating System :: OS Independent
Classifier: Topic :: Scientific/Engineering :: Artificial Intelligence
Classifier: Topic :: Text Processing :: Linguistic
Requires-Python: >=3.8
Requires-Dist: torch>=2.1
Requires-Dist: numpy>=1.26
